daprly/__init__.py
daprly/dapr_client.py
daprly-1.0.1.dist-info/LICENSE
daprly-1.0.1.dist-info/METADATA
daprly-1.0.1.dist-info/WHEEL
daprly-1.0.1.dist-info/top_level.txt
daprly-1.0.1.dist-info/RECORD
